jupyterlab_lsp/__init__.py
jupyterlab_lsp/_paths.py
jupyterlab_lsp/_version.py
jupyterlab_lsp/install.json
jupyterlab_lsp/labextensions/@jupyter-lsp/jupyterlab-lsp/package.json
jupyterlab_lsp/labextensions/@jupyter-lsp/jupyterlab-lsp/schemas/@jupyter-lsp/jupyterlab-lsp/completion.json
jupyterlab_lsp/labextensions/@jupyter-lsp/jupyterlab-lsp/schemas/@jupyter-lsp/jupyterlab-lsp/diagnostics.json
jupyterlab_lsp/labextensions/@jupyter-lsp/jupyterlab-lsp/schemas/@jupyter-lsp/jupyterlab-lsp/highlights.json
jupyterlab_lsp/labextensions/@jupyter-lsp/jupyterlab-lsp/schemas/@jupyter-lsp/jupyterlab-lsp/hover.json
jupyterlab_lsp/labextensions/@jupyter-lsp/jupyterlab-lsp/schemas/@jupyter-lsp/jupyterlab-lsp/jump_to.json
jupyterlab_lsp/labextensions/@jupyter-lsp/jupyterlab-lsp/schemas/@jupyter-lsp/jupyterlab-lsp/package.json.orig
jupyterlab_lsp/labextensions/@jupyter-lsp/jupyterlab-lsp/schemas/@jupyter-lsp/jupyterlab-lsp/plugin.json
jupyterlab_lsp/labextensions/@jupyter-lsp/jupyterlab-lsp/schemas/@jupyter-lsp/jupyterlab-lsp/rename.json
jupyterlab_lsp/labextensions/@jupyter-lsp/jupyterlab-lsp/schemas/@jupyter-lsp/jupyterlab-lsp/signature.json
jupyterlab_lsp/labextensions/@jupyter-lsp/jupyterlab-lsp/schemas/@jupyter-lsp/jupyterlab-lsp/symbol.json
jupyterlab_lsp/labextensions/@jupyter-lsp/jupyterlab-lsp/schemas/@jupyter-lsp/jupyterlab-lsp/syntax_highlighting.json
jupyterlab_lsp/labextensions/@jupyter-lsp/jupyterlab-lsp/static/224.8e4b125226225aa8fca7.js
jupyterlab_lsp/labextensions/@jupyter-lsp/jupyterlab-lsp/static/224.8e4b125226225aa8fca7.js.map
jupyterlab_lsp/labextensions/@jupyter-lsp/jupyterlab-lsp/static/240.134dfe868d23d9df1461.js
jupyterlab_lsp/labextensions/@jupyter-lsp/jupyterlab-lsp/static/240.134dfe868d23d9df1461.js.map
jupyterlab_lsp/labextensions/@jupyter-lsp/jupyterlab-lsp/static/292.065b5526d8893b656a5a.js
jupyterlab_lsp/labextensions/@jupyter-lsp/jupyterlab-lsp/static/292.065b5526d8893b656a5a.js.LICENSE.txt
jupyterlab_lsp-5.1.1.dist-info/licenses/LICENSE
jupyterlab_lsp-5.1.1.dist-info/METADATA
jupyterlab_lsp-5.1.1.dist-info/WHEEL
jupyterlab_lsp-5.1.1.dist-info/top_level.txt
jupyterlab_lsp-5.1.1.dist-info/RECORD
