Metadata-Version: 2.4
Name: jupyterlab-lsp
Version: 5.1.1
Summary: Coding assistance for JupyterLab with Language Server Protocol
Author: JupyterLab-LSP Development Team
Author-email: project.jupyter@gmail.com
License: BSD-3-Clause
Project-URL: Bug Tracker, https://github.com/jupyter-lsp/jupyterlab-lsp/issues
Project-URL: Documentation, https://jupyterlab-lsp.readthedocs.io/
Project-URL: Source Code, https://github.com/jupyter-lsp/jupyterlab-lsp
Keywords: Interactive,Language Server,LSP,JupyterLab,JupyterLab4
Classifier: Framework :: Jupyter
Classifier: Framework :: Jupyter :: JupyterLab
Classifier: Framework :: Jupyter :: JupyterLab :: 4
Classifier: Framework :: Jupyter :: JupyterLab :: Extensions
Classifier: Framework :: Jupyter :: JupyterLab :: Extensions :: Prebuilt
Classifier: Intended Audience :: Developers
Classifier: Intended Audience :: End Users/Desktop
Classifier: Intended Audience :: Information Technology
Classifier: License :: OSI Approved :: BSD License
Classifier: Programming Language :: Python
Requires-Python: >=3.8
License-File: LICENSE
Requires-Dist: jupyter_lsp>=2.0.0
Requires-Dist: jupyterlab<5.0.0a0,>=4.1.0
Dynamic: license-file
